mpathic/__init__.py
mpathic/data/sortseq/full-0/.DS_Store
mpathic/data/sortseq/full-0/bin_1.txt
mpathic/data/sortseq/full-0/bin_2.txt
mpathic/data/sortseq/full-0/bin_3.txt
mpathic/data/sortseq/full-0/bin_4.txt
mpathic/data/sortseq/full-0/crp_model.txt
mpathic/data/sortseq/full-0/data.txt
mpathic/data/sortseq/full-0/data_small.txt
mpathic/data/sortseq/full-0/data_tiny.txt
mpathic/data/sortseq/full-0/files.txt
mpathic/data/sortseq/full-0/genome_ecoli_1000lines.fa
mpathic/data/sortseq/full-0/library.txt
mpathic/data/sortseq/full-0/rnap_model.txt
mpathic/docs/.DS_Store
mpathic/docs/Makefile
mpathic/docs/build/doctrees/Documentation.doctree
mpathic/docs/build/doctrees/environment.pickle
mpathic/docs/build/doctrees/evaluate_model.doctree
mpathic/docs/build/doctrees/examples.doctree
mpathic/docs/build/doctrees/index.doctree
mpathic/docs/build/doctrees/learn_model.doctree
mpathic/docs/build/doctrees/profile_freq.doctree
mpathic/docs/build/doctrees/profile_info.doctree
mpathic/docs/build/doctrees/profile_mutrate.doctree
mpathic/docs/build/doctrees/scan_model.doctree
mpathic/docs/build/doctrees/simulate_library.doctree
mpathic/docs/build/doctrees/simulate_sort.doctree
mpathic/docs/build/doctrees/tutorial.doctree
mpathic/docs/build/html/.buildinfo
mpathic/docs/build/html/Documentation.html
mpathic/docs/build/html/evaluate_model.html
mpathic/docs/build/html/examples.html
mpathic/docs/build/html/genindex.html
mpathic/docs/build/html/index.html
mpathic/docs/build/html/learn_model.html
mpathic/docs/build/html/objects.inv
mpathic/docs/build/html/profile_freq.html
mpathic/docs/build/html/profile_info.html
mpathic/docs/build/html/profile_mutrate.html
mpathic/docs/build/html/scan_model.html
mpathic/docs/build/html/search.html
mpathic/docs/build/html/searchindex.js
mpathic/docs/build/html/simulate_library.html
mpathic/docs/build/html/simulate_sort.html
mpathic/docs/build/html/tutorial.html
mpathic/docs/build/html/_downloads/Kinney2010.pdf
mpathic-0.6.dist-info/LICENSE.txt
mpathic-0.6.dist-info/METADATA
mpathic-0.6.dist-info/RECORD
mpathic-0.6.dist-info/WHEEL
mpathic-0.6.dist-info/top_level.txt
