Metadata-Version: 2.1
Name: mpathic
Version: 0.6
Summary: Tools for analysis of Sort-Seq experiments.
Home-page: UNKNOWN
Author: Bill Ireland, Ammmar Tareen, Justin Kinney
Author-email: tareen@cshl.edu
License: UNKNOWN
Platform: UNKNOWN
Classifier: Development Status :: 3 - Alpha
Classifier: License :: OSI Approved :: MIT License
Classifier: Programming Language :: Python :: 2.7
Classifier: Programming Language :: Python :: 3.6
Classifier: Topic :: Scientific/Engineering :: Mathematics
Requires-Dist: alabaster (==0.7.10)
Requires-Dist: Babel (==2.5.3)
Requires-Dist: backports.functools-lru-cache (==1.5)
Requires-Dist: biopython (==1.71)
Requires-Dist: certifi (==2018.4.16)
Requires-Dist: chardet (==3.0.4)
Requires-Dist: cvxopt (==1.1.9)
Requires-Dist: cycler (==0.10.0)
Requires-Dist: Cython (==0.28.1)
Requires-Dist: docutils (==0.14)
Requires-Dist: idna (==2.6)
Requires-Dist: imagesize (==1.0.0)
Requires-Dist: Jinja2 (==2.10)
Requires-Dist: kiwisolver (==1.0.1)
Requires-Dist: MarkupSafe (==1.0)
Requires-Dist: matplotlib (==2.2.2)
Requires-Dist: mpmath (==1.0.0)
Requires-Dist: numpy (==1.14.2)
Requires-Dist: packaging (==17.1)
Requires-Dist: pandas (==0.22.0)
Requires-Dist: Pygments (==2.2.0)
Requires-Dist: pymc (==2.3.6)
Requires-Dist: pyparsing (==2.2.0)
Requires-Dist: python-dateutil (==2.7.2)
Requires-Dist: pytz (==2018.4)
Requires-Dist: requests (==2.18.4)
Requires-Dist: scikit-learn (==0.19.1)
Requires-Dist: scipy (==1.0.1)
Requires-Dist: six (==1.11.0)
Requires-Dist: sklearn (==0.0)
Requires-Dist: snowballstemmer (==1.2.1)
Requires-Dist: Sphinx (==1.7.3)
Requires-Dist: sphinxcontrib-websupport (==1.0.1)
Requires-Dist: typing (==3.6.4)
Requires-Dist: urllib3 (==1.22)
Requires-Dist: weblogo (==3.6.0)
Requires-Dist: seaborn (==0.9.0)
